setup.py
tglmsm_distributions/Binomialdistribution.py
tglmsm_distributions/Gaussiandistribution.py
tglmsm_distributions/Generaldistribution.py
tglmsm_distributions/__init__.py
tglmsm_distributions.egg-info/PKG-INFO
tglmsm_distributions.egg-info/SOURCES.txt
tglmsm_distributions.egg-info/dependency_links.txt
tglmsm_distributions.egg-info/not-zip-safe
tglmsm_distributions.egg-info/top_level.txt